django_pgtools-0.4.2.dist-info/METADATA
django_pgtools-0.4.2.dist-info/WHEEL
django_pgtools-0.4.2.dist-info/metadata.json
django_pgtools-0.4.2.dist-info/DESCRIPTION.rst
django_pgtools-0.4.2.dist-info/top_level.txt
django_pgtools-0.4.2.dist-info/RECORD
pgtools/dbrole.py
pgtools/dbuser.py
pgtools/tests.py
pgtools/utils.py
pgtools/models.py
pgtools/__init__.py
pgtools/decorators.py
pgtools/management/__init__.py
pgtools/management/commands/createuser.py
pgtools/management/commands/grantuser.py
pgtools/management/commands/deleteuser.py
pgtools/management/commands/__init__.py
pgtools/management/commands/listusers.py
