Metadata-Version: 2.0
Name: django-pgtools
Version: 0.4.2
Summary: Set of Django management commands for handling various aspects of managing PostgreSQL database.
Home-page: https://launchpad.net/django-pgtools
Author: Canonical ISD
Author-email: canonical-isd@lists.launchpad.net
License: AGPLv3
Platform: UNKNOWN
Requires: django (>=1.6)
